MANIFEST.in
setup.py
hellotrik/__init__.py
hellotrik.egg-info/PKG-INFO
hellotrik.egg-info/SOURCES.txt
hellotrik.egg-info/dependency_links.txt
hellotrik.egg-info/requires.txt
hellotrik.egg-info/top_level.txt
hellotrik.egg-info/zip-safe
hellotrik/examples/__init__.py
hellotrik/examples/hw.py
hellotrik/examples/mnist.py
hellotrik/kernel/__init__.py
hellotrik/kernel/uwnet.py
hellotrik/examples/__init__.py
hellotrik/examples/hw.py
hellotrik/examples/mnist.py
hellotrik/kernel/__init__.py
hellotrik/kernel/dog.jpg
hellotrik/kernel/libuwimg.a
hellotrik/kernel/libuwimg.so
hellotrik/kernel/uwnet.py
hellotrik/kernel/__pycache__/__init__.cpython-35.pyc
hellotrik/kernel/__pycache__/uwnet.cpython-35.pyc